__init__.py
django_owm/__init__.py
django_owm/admin.py
django_owm/app_settings.py
django_owm/apps.py
django_owm/forms.py
django_owm/tasks.py
django_owm/urls.py
django_owm/validators.py
django_owm/views.py
django_owm/management/commands/create_location.py
django_owm/management/commands/delete_location.py
django_owm/management/commands/list_locations.py
django_owm/management/commands/manual_weather_fetch.py
django_owm/migrations/__init__.py
django_owm/models/__init__.py
django_owm/models/abstract.py
django_owm/models/base.py
django_owm/models/concrete.py
django_owm/utils/__init__.py
django_owm/utils/api.py
django_owm/utils/saving.py
django_owm-2024.10.2.dist-info/LICENSE
django_owm-2024.10.2.dist-info/METADATA
django_owm-2024.10.2.dist-info/WHEEL
django_owm-2024.10.2.dist-info/top_level.txt
django_owm-2024.10.2.dist-info/RECORD
