Metadata-Version: 2.1
Name: django-owm
Version: 2024.10.2
Summary: Weather from the Open Weather Map APIs
Author-email: Jack Linke <jacklinke@gmail.com>
License: MIT
Project-URL: Changelog, https://github.com/OmenApps/django-owm/releases
Project-URL: Homepage, https://github.com/OmenApps/django-owm
Project-URL: Repository, https://github.com/OmenApps/django-owm
Project-URL: Documentation, https://django-owm.readthedocs.io
Project-URL: Issues, https://github.com/OmenApps/django-owm/issues
Classifier: Environment :: Web Environment
Classifier: Framework :: Django
Classifier: Framework :: Django :: 4.2
Classifier: Framework :: Django :: 5.0
Classifier: Framework :: Django :: 5.1
Classifier: Development Status :: 4 - Beta
Classifier: Intended Audience :: Developers
Classifier: License :: OSI Approved :: MIT License
Classifier: Operating System :: OS Independent
Classifier: Programming Language :: Python
Classifier: Programming Language :: Python :: 3
Classifier: Programming Language :: Python :: 3.10
Classifier: Programming Language :: Python :: 3.11
Classifier: Programming Language :: Python :: 3.12
Classifier: Topic :: Internet :: WWW/HTTP
Classifier: Topic :: Internet :: WWW/HTTP :: Dynamic Content
Classifier: Topic :: Software Development :: Libraries :: Python Modules
Requires-Python: <4.0,>=3.10
License-File: LICENSE
Requires-Dist: django >=4.2
Requires-Dist: click >=8.1.7
Requires-Dist: requests >=2.31.0
Requires-Dist: celery >=5.2.0
Provides-Extra: dev
Requires-Dist: Pygments >=2.18.0 ; extra == 'dev'
Requires-Dist: bandit >=1.7.8 ; extra == 'dev'
Requires-Dist: black >=24.4.2 ; extra == 'dev'
Requires-Dist: coverage[toml] >=7.5.1 ; extra == 'dev'
Requires-Dist: darglint >=1.8.1 ; extra == 'dev'
Requires-Dist: flake8 >=7.0.0 ; extra == 'dev'
Requires-Dist: flake8-bugbear >=24.4.26 ; extra == 'dev'
Requires-Dist: flake8-docstrings >=1.7.0 ; extra == 'dev'
Requires-Dist: flake8-rst-docstrings >=0.3.0 ; extra == 'dev'
Requires-Dist: furo >=2024.8.6 ; extra == 'dev'
Requires-Dist: isort >=5.13.2 ; extra == 'dev'
Requires-Dist: nox >=2024.4.15 ; extra == 'dev'
Requires-Dist: nox-poetry >=1.0.3 ; extra == 'dev'
Requires-Dist: poetry-plugin-export >=1.8.0 ; extra == 'dev'
Requires-Dist: pep8-naming >=0.14.1 ; extra == 'dev'
Requires-Dist: pre-commit >=3.7.1 ; extra == 'dev'
Requires-Dist: pre-commit-hooks >=4.6.0 ; extra == 'dev'
Requires-Dist: pytest >=8.2.1 ; extra == 'dev'
Requires-Dist: pytest-cov >=5.0.0 ; extra == 'dev'
Requires-Dist: pytest-django >=4.8.0 ; extra == 'dev'
Requires-Dist: pyupgrade >=3.15.2 ; extra == 'dev'
Requires-Dist: safety >=3.2.0 ; extra == 'dev'
Requires-Dist: sphinx >=8.1.0 ; extra == 'dev'
Requires-Dist: sphinx-autobuild >=2024.4.16 ; extra == 'dev'
Requires-Dist: sphinx-click >=6.0.0 ; extra == 'dev'
Requires-Dist: xdoctest[colors] >=1.1.3 ; extra == 'dev'
Requires-Dist: myst-parser >=4.0.0 ; extra == 'dev'
Requires-Dist: redis >=4.0.0 ; extra == 'dev'
